processmining/__init__.py
processmining/discovery/__init__.py
processmining/discovery/ocdfg/__init__.py
processmining/discovery/ocdfg/constants.py
processmining/discovery/ocdfg/visualize.py
processmining/discovery/ocdfg/markov/__init__.py
processmining/discovery/ocdfg/markov/cluster_tuning.py
processmining/discovery/ocdfg/markov/constants.py
processmining/discovery/ocdfg/markov/discover.py
processmining/discovery/ocdfg/markov/visualize.py
processmining/log/__init__.py
processmining/log/ocel/__init__.py
processmining/log/ocel/filter.py
processmining/log/ocel/olap.py
processmining/log/xes/__init__.py
processmining/log/xes/filter.py
processmining/log/xes/olap.py
processmining/loghandlers/__init__.py
processmining/loghandlers/constants.py
processmining/loghandlers/ocel.py
processmining/loghandlers/tocel.py
processmining-1.0.17.dist-info/METADATA
processmining-1.0.17.dist-info/WHEEL
processmining-1.0.17.dist-info/top_level.txt
processmining-1.0.17.dist-info/RECORD
