Metadata-Version: 2.1
Name: processmining
Version: 1.0.17
Summary: Python processmining Package
Home-page: https://github.com/jalaliamin/processmining
Author: Amin Jalali
License: MIT
Platform: UNKNOWN
Requires-Dist: pandas
Requires-Dist: numpy
Requires-Dist: pm4py
Requires-Dist: matplotlib
Requires-Dist: seaborn
